LICENSE
README.md
dsfr/__init__.py
dsfr/admin.py
dsfr/apps.py
dsfr/checksums.py
dsfr/constants.py
dsfr/context_processors.py
dsfr/enums.py
dsfr/fields.py
dsfr/forms.py
dsfr/models.py
dsfr/utils.py
dsfr/widgets.py
dsfr/fixtures/init.json
dsfr/locale/fr/LC_MESSAGES/django.mo
dsfr/locale/fr/LC_MESSAGES/django.po
dsfr/management/__init__.py
dsfr/management/commands/__init__.py
dsfr/management/commands/integrity_checksums.py
dsfr/management/commands/make_icon_picker_files.py
dsfr/management/commands/trim_dist.py
dsfr/migrations/0001_initial.py
dsfr/migrations/0002_auto_20211209_1557.py
dsfr/migrations/0003_alter_dsfrconfig_accessibility_status.py
dsfr/migrations/0004_dsfrconfig_beta_tag_dsfrconfig_operator_logo_alt_and_more.py
dsfr/migrations/0005_dsfrconfig_notice.py
dsfr/migrations/0006_alter_dsfrconfig_accessibility_status.py
dsfr/migrations/0007_dsfrconfig_newsletter_description_and_more.py
dsfr/migrations/0008_alter_dsfrsocialmedia_options_dsfrconfig_language_and_more.py
dsfr/migrations/0009_dsfrconfig_notice_type_alter_dsfrconfig_notice.py
dsfr/migrations/0010_dsfrconfig_notice_icon_class_alter_dsfrconfig_notice_and_more.py
dsfr/migrations/0011_rename_notice_dsfrconfig_notice_title.py
dsfr/migrations/0012_dsfrconfig_notice_description_and_more.py
dsfr/migrations/__init__.py
dsfr/static/css/dsfr-code.css
dsfr/static/css/dsfr-django-overrides.css
dsfr/static/django-dsfr/icon-picker/README.md
dsfr/static/django-dsfr/icon-picker/assets/icons-libraries/dsfr-arrows.json
dsfr/static/django-dsfr/icon-picker/assets/icons-libraries/dsfr-buildings.json
dsfr/static/django-dsfr/icon-picker/assets/icons-libraries/dsfr-business.json
dsfr/static/django-dsfr/icon-picker/assets/icons-libraries/dsfr-communication.json
dsfr/static/django-dsfr/icon-picker/assets/icons-libraries/dsfr-design.json
dsfr/static/django-dsfr/icon-picker/assets/icons-libraries/dsfr-development.json
dsfr/static/django-dsfr/icon-picker/assets/icons-libraries/dsfr-device.json
django_dsfr-3.3.1.dist-info/METADATA
django_dsfr-3.3.1.dist-info/WHEEL
django_dsfr-3.3.1.dist-info/licenses/LICENSE
django_dsfr-3.3.1.dist-info/RECORD
