Metadata-Version: 2.4
Name: django-dsfr
Version: 3.3.1
Summary: Integrate the French government Design System into a Django app
Project-URL: documentation, https://numerique-gouv.github.io/django-dsfr
Project-URL: homepage, https://github.com/numerique-gouv/django-dsfr
Project-URL: repository, https://github.com/numerique-gouv/django-dsfr
Author-email: Sylvain Boissel <sylvain.boissel@beta.gouv.fr>
License-Expression: MIT
License-File: LICENSE
Keywords: django,dsfr
Classifier: Development Status :: 5 - Production/Stable
Classifier: Environment :: Web Environment
Classifier: Framework :: Django
Classifier: Framework :: Django :: 4.2
Classifier: Framework :: Django :: 5.0
Classifier: Framework :: Django :: 5.1
Classifier: Framework :: Django :: 5.2
Classifier: Framework :: Django :: 6.0
Classifier: Intended Audience :: Developers
Classifier: License :: OSI Approved :: MIT License
Classifier: Operating System :: OS Independent
Classifier: Programming Language :: Python :: 3
Classifier: Programming Language :: Python :: 3.10
Classifier: Programming Language :: Python :: 3.11
Classifier: Programming Language :: Python :: 3.12
Classifier: Programming Language :: Python :: 3.13
Classifier: Programming Language :: Python :: 3.14
Classifier: Topic :: Software Development :: Libraries
Classifier: Topic :: Utilities
Requires-Python: <4.0,>=3.10
Requires-Dist: django-crispy-forms<3.0,>=2.0
Requires-Dist: django-widget-tweaks<2.0.0,>=1.4.12
Requires-Dist: django>4.2.27
Requires-Dist: requests<3.0.0,>=2.26.0
